README.md
setup.py
cosmoplib/__init__.py
cosmoplib/myfunctions.py
cosmoplib.egg-info/PKG-INFO
cosmoplib.egg-info/SOURCES.txt
cosmoplib.egg-info/dependency_links.txt
cosmoplib.egg-info/requires.txt
cosmoplib.egg-info/top_level.txt