Metadata-Version: 2.1
Name: cosmoplib
Version: 0.1.0
Summary: COSMOP Library
Home-page: UNKNOWN
Author: Luke Lorentzatos
License: UH
Platform: UNKNOWN
